{
  "branch": "วิทย์-คุณภาพ",
  "teachers": ["ครูไผท สะอาดยิ่ง", "ครูสายสุนีย์ วงศ์สวัสดิ์"],
  "data": {
    "1:1": { "name": "ฟิสิกส์", "teacher": "ครูนพล" },
    "1:2": { "name": "ฟิสิกส์", "teacher": "ครูนพล" },
    "1:3": { "name": "คณิตศาสตร์", "teacher": "ครูพิมลพรรณ" },
    "1:4": { "name": "การอ่าน", "teacher": "ครูไผท" },
    "1:5": { "name": "ประวัติศาสตร์", "teacher": "ครูจินตนา" },
    "1:6": { "name": "การอ่าน", "teacher": "ครูDakota" },
    "1:7": { "name": "คณิตศาสตร์", "teacher": "ครูน้ำเพชร" },
    "1:8": { "name": "กิจกรรม", "teacher": null },
    "2:1": { "name": "ชีววิทยา", "teacher": "ครูปรีดากรณ์" },
    "2:2": { "name": "ชีววิทยา", "teacher": "ครูปรีดาภรณ์" },
    "2:3": { "name": "วิทยาศาสตร์", "teacher": "ครูพิพัฒน์" },
    "2:4": { "name": "นาฏศิลป์ไทย", "teacher": "ครูสุพิชฌาย์" },
    "2:5": { "name": "HR", "teacher": "ครูไผท" },
    "2:6": { "name": "ภาษาอังกฤษ", "teacher": "ครูไผท" },
    "2:7": { "name": "กฎหมายน่ารู้", "teacher": "ครูวีระชัย" },
    "2:8": { "name": "ภาษาไทย", "teacher": "ครูพิมพิศา" },
    "3:1": { "name": "ภาษาไทย", "teacher": "ครูพิมพิศา" },
    "3:2": { "name": "เศรษฐศาสตร์", "teacher": "ครูจุฑามาศ" },
    "3:3": { "name": "คุณภาพชีวิต", "teacher": "ครูสายสุนิย์" },
    "3:4": { "name": "คณิตศาสตร์", "teacher": "ครูพิมลพรรณ" },
    "3:5": { "name": "วิทยาศาสตร์", "teacher": "ครูนพล" },
    "3:6": { "name": "สุขศึกษา", "teacher": "ครูกมลวรรณ" },
    "3:7": { "name": "คณิตศาสตร์", "teacher": "ครูน้ำเพชร" },
    "3:8": { "name": "พลศึกษา", "teacher": "ครูบรรจบ" },
    "4:1": { "name": "คุณภาพชีวิต", "teacher": "ครูสายสุนีย์" },
    "4:2": { "name": "แนะแนว", "teacher": "ครูจุฑาทิพย์" },
    "4:3": { "name": "คณิตศาสตร์", "teacher": "ครูพิมลพรรณ" },
    "4:4": { "name": "เศรษฐศาสตร์", "teacher": "ครูจุฑามาศ" },
    "4:5": { "name": "คณิตศาสตร์", "teacher": "ครูน้ำเพชร" },
    "4:6": { "name": "เคมี", "teacher": "ครูพิพัฒน์" },
    "4:7": { "name": "เคมี", "teacher": "ครูพิพัฒน์" },
    "5:1": { "name": "ฟิสิกส์", "teacher": "ครูนพล" },
    "5:2": { "name": "ชีววิทยา", "teacher": "ครูปรีดาภรณ์" },
    "5:3": { "name": "ภาษาอังกฤษ", "teacher": "ครูไผท" }
  }
}
