{
  "meta": {
    "branch": "วิทย์-คณิต",
    "teacher": [
      "ครูพิษณุ จันทรเสวต",
      "ครูลัดดา ฉิมพาลี"
    ],
    "room": "443"
  },
  "body": {
    "1": {
      "1": [
        "สุขศึกษา",
        "ครูสิรากร"
      ],
      "2": [
        "ชีววิทยา",
        "ครูสหยศ"
      ],
      "3": [
        "ชีววิทยา",
        "ครูสหยศ"
      ],
      "4": [
        "คณิตศาสตร์",
        "ครูโสมรัศมิ์"
      ],
      "5": [
        "เศรษฐศาสตร์",
        "ครูจิตสุภา"
      ],
      "6": [
        "พลศึกษา",
        "ครูพุฒิพงศ์"
      ],
      "7": [
        "ภาษาอังกฤษ",
        "ครูอมรรัตน์"
      ],
      "8": [
        "กิจกรรม"
      ]
    },
    "2": {
      "1": [
        "เคมี",
        "ครูณรงค์ฤทธิ์"
      ],
      "2": [
        "เคมี",
        "ครูณรงค์ฤทธิ์"
      ],
      "3": [
        "ชีววิทยา",
        "ครูสหยศ"
      ],
      "4": [
        "คณิตศาสตร์",
        "ครูชลธิชา"
      ],
      "5": [
        "HR",
        "ครูพิษณุ"
      ],
      "6": [
        "คณิตศาสตร์",
        "ครูโสมรัศมิ์"
      ],
      "7": [
        "วิทยาศาสตร์",
        "ครูพิษณุ"
      ],
      "8": []
    },
    "3": {
      "1": [
        "พื้นฐานดำรงฯ",
        "ครูกิติยา"
      ],
      "2": [
        "พื้นฐานดำรงฯ",
        "ครูกิติยา"
      ],
      "3": [
        "คณิตศาสตร์",
        "ครูโสมรัศมิ์"
      ],
      "4": [
        "เศรษฐศาสตร์",
        "ครูจิตสุภา"
      ],
      "5": [
        "คณิตศาสตร์",
        "ครูชลธิชา"
      ],
      "6": [
        "ภาษาไทย",
        "ครูณัฐวร"
      ],
      "7": [
        "ฟิสิกส์",
        "ครูพิษณุ"
      ],
      "8": [
        "ฟิสิกส์",
        "ครูพิษณุ"
      ]
    },
    "4": {
      "1": [
        "การอ่าน",
        "ครูSanti"
      ],
      "2": [
        "ภาษาอังกฤษ",
        "ครูอมรรัตน์"
      ],
      "3": [
        "การอ่าน",
        "ครูอมรรัตน์"
      ],
      "4": [
        "ประวัติศาสตร์เศรษฐกิจ",
        "ครูจิตสุภา"
      ],
      "5": [
        "นาฏศิลป์สากล",
        "ครูทรงกลด"
      ],
      "6": [
        "วิทยาศาสตร์",
        "ครูณรงค์ฤทธิ์"
      ],
      "7": [
        "คณิตศาสตร์",
        "ครูชลธิชา"
      ],
      "8": []
    },
    "5": {
      "1": [
        "แนะแนว",
        "ครูฐิติณัฏฐ์"
      ],
      "2": [
        "ภาษาไทย",
        "ครูณัฐวร"
      ],
      "3": [
        "ฟิสิกส์",
        "ครูพิษณุ"  
      ]
    }
  }
}