{
  "meta": {
    "branch": "ภาษา-ฝรั่งเศส",
    "teacher": [
      "ครูจักรชัย ศรีวรเวทย์",
      " "
    ],
    "room": "835"
  },
  "body": {
    "1": {
      "1": [
        "อังกฤษท่องเที่ยว",
        "ครูอมรรัตน์"
      ],
      "2": [
        "เศรษฐศาสตร์",
        "ครูรัฐธรรมนูญ"
      ],
      "3": [
        "ภาษาฝรั่งเศส",
        "ครูเฉลิมวุฒิ"
      ],
      "4": [
         "วิทยาศาสตร์",
        "ครูธนิดา"
      ],
      "5": [
       "ภาษาอังกฤษ",
        "ครูณัฐพร"
      ],
      "6": [
        "สุขศึกษา",
        "ครูกมลวรรณ"
      ],
      "7": [
         "วรรณคดีมรดก",
        "ครูพิมพิศา"
      ],
      "8": [
        "กิจกรรม"
      ]
    },
    "2": {
      "1": [
        "พื้นฐานดำรงฯ",
        "ครูศศิธร"
      ],
      "2": [
        "พื้นฐานดำรงฯ",
        "ครูศศิธร"
      ],
      "3": [
        "พลศึกษา",
        "ครูบรรจบ"
      ],
      "4": [
        "เสริมทักษะ",
        "ครูAldrin"
      ],
      "5": [
        "HR",
        "ครูจักรชัย"
      ],
      "6": [
        "ภาษาฝรั่งเศส",
        "ครูเฉลิมวุฒิ"
      ],
      "7": [
              "ภาษาอังกฤษ",
        "ครูณัฐพร"
      ],
      "8": []
    },
    "3": {
      "1": [
        "ภาษาฝรั่งเศส",
        "ครูเฉลิมวุฒิ"
      ],
      "2": [
        "วิทยาศาสตร์",
        "ครูธนิดา"
      ],
      "3": [
        "ประวัติศาสตร์เศรษฐกิจ",
        "ครูรัฐธรรมนูญ"
      ],
      "4": [
        "นาฏศิลป์สากล",
        "ครูทรงกลด"
      ],
      "5": [
        "คณิตศาสตร์",
        "ครูพิมลวรรณ"
      ],
      "6": [
          "ภาษาฝรั่งเศส",
        "ครูเฉลิมวุฒิ"
      ],
      "7": [
          "กาษาฝรั่งเศสฟัง-พูด",
        "ครูวรณัน"
      ],
      "8": [
    "การอ่าน",
    "ครูTheodore"
      ]
    },
    "4": {
      "1": [
        "ภาษาไทย",
        "ครูจักรชัย"
      ],
      "2": [
        "คณิตศาสตร์",
        "ครูพิมลพรรณ"
      ],
      "3": [
        "แนะแนว",
        "ครูจุฑาทิพย์"
      ],
      "4": [
        "ภาษาฝรั่งเศส",
        "ครูวรณัน"
      ],
      "5": [
        "วรรณคดมีรดก",
        "ครูพิมพิศา"
      ],
      "6": [
          "ภาษาฝรั่งเศส",
        "ครูเฉลิมวุฒิ"
      ],
      "7": [
             "เศรษฐศาสตร์",
        "ครูรัฐธรรมนูญ"
      ]
    },
    "5": {
      "1": [
        "ภาษาฝรั่งเศสฟัง-พูด",
        "ครูวรณัน"
      ],
      "2": [
        "การอ่าน",
        "ครูณัฐพร"
      ],
      "3": [
        "ภาษาไทย",
        "ครูจักรชัย"
      ]
    }
  }
}