{
  "meta": {
    "branch": "ภาษา-คณิต",
    "teacher": [
      "ครูน้ำ ทิพย์ชัยวงศ์",
      "ครูพลธรา ไทยน้อย"
    ],
    "room": "225"
  },
  "body": {
    "1": {
      "1": [
        "คณิตศาสตร์",
        "ครูพลธรา"
      ],
      "2": [
        "วิทยาศาสตร์",
        "ครูวรนันทน์"
      ],
      "3": [
        "ภาษาอังกฤษ",
        "ครูเปรมจิรัณ"
      ],
      "4": [
        "แนะแนว"
      ],
      "5": [
        "อาเซียนศึกษา",
        "ครูชัยภัทร"
      ],
      "6": [
        "พลศึกษา",
        "ประเดิมชัย"
      ],
      "7": [
        "การอ่าน",
        "ครูเปรมจิรัณ"
      ],
      "8": [
        "กิจกรรม"
      ]
    },
    "2": {
      "1": [
        "เสริมทักษะ",
        "ครูWilliam"
      ],
      "2": [
        "การอ่าน",
        "A⭑Crist"
      ],
      "3": [
        "สุขศึกษา",
        "ครูอธิปัตย์"
      ],
      "4": [
        "คณิตศาสตร์",
        "ครูพลธรา"
      ],
      "5": [
        "คณิตศาสตร์",
        "ครูบุญฤทธิ์"
      ],
      "6": [
        "การเขียน",
        "ครูน้ำทิพย์"
      ],
      "7": [],
      "8": []
    },
    "3": {
      "1": [
        "ESP",
        "ครูMichael"
      ],
      "2": [
        "คณิตศาสตร์",
        "ครูณัฐพล"
      ],
      "3": [
        "คณิตศาสตร์",
        "ครูบุญฤทธิ์"
      ],
      "4": [
        "ภาษาไทย",
        "ครูล่าพูน"
      ],
      "5": [
        "ฯ",
        "ครูชัยภัทร"
      ],
      "6": [
        "วิทยาศาสตร์",
        "ครูวรนันทน์"
      ],
      "7": [],
      "8": []
    },
    "4": {
      "1": [
        "ESP",
        "ครูอสมาภรณ์"
      ],
      "2": [
        "คณิตศาสตร์",
        "ครูณัฐพล"
      ],
      "3": [
        "คณิตศาสตร์",
        "ครูบุญฤทธิ์"
      ],
      "4": [
        "ภาษาไทย",
        "ครูล่าพูน"
      ],
      "5": [
        "HR",
        "ครูพลธรา"
      ],
      "6": [
        "คณิตศาสตร์",
        "ครูพสธรา"
      ],
      "7": [],
      "8": []
    },
    "5": {
      "1": [
        "ประวัติศาสตร์ฯ",
        "ครูชัยภัทร"
      ],
      "2": [
        "ภาษาอังกฤษ",
        "ครูเปรมจิรัณ"
      ],
      "3": [
        "การเขียน",
        "ครูน้ำทิพย์"
      ]
    }
  }
}