{
  "meta": {
    "branch": "วิทย์-คณิต",
    "teacher": ["ครูชมธาดา ปริเมธาชัย", "ครูชุตินันท์ พ่วงขาว"],
    "room": "68"
  },
  "body": {
    "1": {
      "1": ["คณิตศาสตร์", "ครูสิทธิพงษ์"],
      "2": ["เคมี", "ครูพิมพ์ชมภู"],
      "3": ["ภาษาอังกฤษ", "ครูชมธาดา"],
      "4": ["สังคมศึกษา", "ครูสราวุธ"],
      "5": ["วิทยาการคำนวณ", "ครูชุตินันท์"],
      "6": ["วิทยาการคำนวณ", "ครูชุตินันท์"],
      "7": ["พลศึกษา", "ครูพงศ์ระพี"],
      "8": ["กิจกรรม"]
    },
    "2": {
      "1": ["วิทยาศาสตร์", "ครูคธา"],
      "2": ["คณิตศาสตร์", "ครูรพีพัฒน์"],
      "3": ["ทัศนศิลป์", "ครูสุรัชสานุ์"],
      "4": ["ทัศนศิลป์", "ครูสุรัชสานุ์"],
      "5": ["ฟิสิกส์", "ครูสตรีรัตน์"],
      "6": ["ฟิสิกส์", "ครูสตรีรัตน์"],
      "7": ["การอ่าน", "ครู James"],
      "8": []
    },
    "3": {
      "1": ["คณิตศาสตร์", "ครูรพีพัฒน์"],
      "2": ["การอ่าน", "ครูชมธาดา"],
      "3": ["เคมี", "ครูพิมพ์ชมภู"],
      "4": ["เคมี", "ครูพิมพ์ชมภู"],
      "5": ["ภาษาอังกฤษ(HR)", "ครูชมธาดา"],
      "6": ["พระพุทธศาสนา", "ครูสราวุธ"],
      "7": ["แนะแนว", "ครูพิชญาพร"],
      "8": ["คณิตศาสตร์", "ครูสิทธิพงษ์"]
    },
    "4": {
      "1": ["ชีววิทยา", "ครูคธา"],
      "2": ["ชีววิทยา", "ครูคธา"],
      "3": ["คณิตศาสตร์", "ครูรพีพัฒน์"],
      "4": ["ภาษาไทย", "ครูอรรคราวุฒิ"],
      "5": ["สังคมศึกษา", "ครูสราวุธ"],
      "6": ["สุขศึกษา", "ครูกนกพร"],
      "7": ["คณิตศาสตร์", "ครูสิทธิพงษ์"],
      "8": []
    },"5": {
    "1": ["ภาษาไทย", "ครูอรรคราวุฒิ"],
    "2": ["วิทยาศาสตร์", "ครูสตรีรัตน์"],
    "3": ["การอ่าน", "ครูชมธาดา"]
  }
}}
