{"meta": {"branch": "ภาษา-ฝรั่งเศส GE", "teacher": ["ครูสราวุธ ศรีเกตุ", "ครูพิมพ์รฎา แก้วไสย"], "room": "65", "opt": 2}, "body": 

{"1": {"1": ["ภาษาฝรั่งเศส", "ครูปุณยวีร์"], "2": ["คณิตศาสตร์", "ครูจุฬา"], "3": ["การออกแบบ", "ครูชุตินันท์"], "4": ["ออกแบบ", "ครูชุตินันท์"], "5": ["เสริมทักษะ", "ครูHereward"], "6": ["ประวัติวรรณคดี", "ครูนฤมล"], "7": ["ภาษาไทย", "ครูคมชาญ"], "8": ["กิจกรรม"]}, 

"2": {"1": ["คณิตศาสตร์", "ครูจุฬา"], "2": ["ประวัติฯการเมือง", "ครูสราวุธ"], "3": ["ภาษาอังกฤษ", "ครูทิพยรัตน์"], "4": ["การอ่าน", "ครูทิพยรัตน์"], "5": ["วิทยาศาสตร์", "ครูสุวิชาดา"], "6": ["ฝรั่งเศส", "ครูคณิศร"], "7": ["ภาษาฝรั่งเศส", "ครูปุณยวีร์"], "8": ["ภาษาไทย", "ครูคมชาญ"]}, 

"3": {"1": ["ภาษาอังกฤษ", "ครูทิพยรัตน์"], "2": ["การอ่าน", "ครูทิพยรัตน์"], "3": ["ภาษาฝรั่งเศส", "ครูปุณยวีร์"], "4": ["สุขศึกษา", "ครูพิชาธรณ์"], "5": ["หน้าที่พลเมือง(HR)", "ครูสราวุธ"], "6": ["ทัศนศิลป์", "ครูกิตตินันทน์"], "7": ["ทัศนศิลป์", "ครูกิตตินันทน์"], "8": ["ภาษาฝรั่งเศส", "ครูคณิศร"]}, 

"4": {"1": ["การอ่าน", "ครูDavid"], "2": ["ประวัติวรรณคดี", "ครูนฤมล"], "3": ["ภาษาฝรั่งเศส", "ครูปุณยวีร์"], "4": ["วิทยาศาสตร์","ครูสุวิชาดา"], "5": ["ภาษาฝรั่งเศส", "ครูปุณยวีร์"], "6": ["สารนิเทศฯ", "ครูวรรณภา"], "7": ["สารนิเทศฯ", "ครูวรรณภา"], "8": ["พลศึกษา", "ครูอัทธ์"]}, 

"5": {"1": ["ภาษาฝรั่งเศส", "ครูปุณยวีร์"], "2": ["แนะแนว", "ครูพิชญาพร"], "3": ["หน้าที่พลเมืองฯ", "ครูสราวุธ"]}}}