{"meta":{"branch":"ภาษา-คณิต","teacher":["ครูธรรมศักดิ์ รัศมีสกุลไกร"," "],"room":"73"},"body":{"1":{"1":["คณิตศาสตร์","ครูบุญฤทธิ์"],"2":["อาเซียนศึกษา","ครูนิตยา"],"3":["การเขียน","ครูอภิชาติ"],"4":["บูรณาการ","(แนะแนว)"],"5":["SELF"],"6":["การอ่าน","AşJames"],"7":["วิทยาศาสตร์","ครูเผด็จ"],"8":["กิจกรรม"]},"2":{"1":["ภาษาอังกฤษ","ครูสุพินดา"],"2":["การเขียน","ครูอภิชาติ"],"3":["การนำเสนอ","ครูพัชรินทร์"],"4":["การนำเสนอง","ครูพัชรินทร์"],"5":["คณิตศาสตร์","ครูบุญฤทธิ์"],"6":[],"7":[],"8":[]},"3":{"1":["เสริมทักษะ","ASMs.Cheryl"],"2":["สุขศึกษา","Açaisonครูณัฐธินี"],"3":["ประวัติศาสตร์","ครูนิตยา"],"4":["คณิตศาสตร์","ครูธรรมศักดิ์"],"5":["การอ่าน","ครูสุพินดา"],"6":["พลศึกษา","ครูพงศ์ระพี"],"7":[],"8":[]},"4":{"1":["ประวัติศาสตร์","ครูนิตยา"],"2":["ประวัติศาสตร์","ครูนิตยา"],"3":["คณิตศาสตร์","ครูธรรมศักดิ์"],"4":["ภาษาอังกฤษ","ครูสุพินดา"],"5":["HR","ครูธรรมศักดิ์"],"6":["ภาษาไทย","ครูจักรชัย"],"7":[],"8":[]},"5":{"1":["ภาษาไทย","ครูจักรชัย"],"2":["RETVASCO","วิทยาศาสตร์","ครูเผด็จ"],"3":["คณิตศาสตร์","ครูธรรมศักดิ์"]}}}