{"meta": {"branch": "วิทย์-คณิต", "teacher": ["ครูสุพินดา ทิพย์เอียด", " "], "room": "80", "opt": 5}, "body": {"1": {"1": ["คณิตศาสตร์", "ครกราดร"], "2": ["คณิตศาสตร์", "ครูวัชรสันต์ส"], "3": ["เคมี", "ครูสมคิด"], "4": ["สุขศึกษา", "ครูณัฐธินี"], "5": ["บูรณาการ", "(แนะแนว)"], "6": ["ภาษาอังกฤษ", "ครูสุพินดา"], "7": ["ชีววิทยา", "ครูอาทิตย์"], "8": ["กิจกรรม"]}, "2": {"1": ["ฟิสิกส์", "ครูอังศนา"], "2": ["ฟิสิกส์", "ครูอังศนา"], "3": ["อาเซียนศึกษา", "ครูสยมภู"], "4": ["คณิตศาสตร์", "ครูกราดร"], "5": ["ชีววิทยา", "ครูอาทิตย์"], "6": ["วิทยาศาสตร์", "ครูเผด็จ"], "7": [], "8": []}, "3": {"1": ["ประวัติศาสตร์", "ครูสยมภู"], "2": ["คณิตศาสตร์", "ครูวัชรสันต์"], "3": ["เคมี", "ครูสมคิด"], "4": ["ฟิสิกส์", "ครูอังศนา"], "5": ["คณิตศาสตร์", "ครูภราดร"], "6": ["ภาษาไทย", "ครูอภิชาติ"], "7": ["ภาษาอังกฤษ", "ครูสุพินดา"], "8": []}, "4": {"1": ["ครูสยมภู"], "2": ["การอ่าน", "ครูJames"], "3": ["พลศึกษา", "ครูจิรวัฒน์"], "4": ["คณิตศาสตร์", "ครูวัชรสันต์"], "5": ["HR", "ครูสุพินดา"], "6": ["เคมี", "ครูสมคิด"], "7": ["ฟิสิกส์", "ครูอังศนา"], "8": []}, "5": {"1": ["ภาษาไทย", "ครูอภิชาติ"], "2": ["ชีววิทยา", "ครูอาทิตย์"], "3": ["การอ่าน", "ครูสุพินดา"]}}}