{
    "meta": {
        "branch": "ภาษา-จีน",
        "teacher": ["ครูกฤตพงศ์ มูลมี", " "],
        "room": "73"
    },
    "body": {
        "1": {
            "1": ["เสริมทักษะ", "ครูF"],
            "2": ["วิทยาศาสตร์", "ครูเผด็จ"],
            "3": ["คณิตศาสตร์", "ครูบุญฤทธิ์"],
            "4": ["SELF"],
            "5": ["ภาษาไทย", "ครูอภิชาติ"],
            "6": ["สังคมศึกษา", "ครูนิตยา"],
            "7": ["สุขศึกษา", "ครูณัฐธินี"],
            "8": ["กิจกรรม"]
        },
        "2": {
            "1": ["ภาษาจีน", "ครูกฤตพงศ์"],
            "2": ["ภาษาไทย", "ครูอภิชาติ"],
            "3": ["ภาษาจีน", "ครูกันต์กนิษฐ"],
            "4": ["หลักภาษาไทย", "ครูสัพพัญญู"],
            "5": ["ภาษาจีน", "ครูกฤตพงศ์"],
            "6": ["สังคมศึกษา", "ครูนิตยา"],
            "7": [],
            "8": []
        },
        "3": {
            "1": ["คณิตศาสตร์", "ครูบุญฤทธิ์"],
            "2": ["ภาษาจีน", "ครูกันต์กนิษฐ"],
            "3": ["ภาษาอังกฤษ", "ครูฤทธิรงค์"],
            "4": ["หลักภาษาไทย", "ครูสัพพัญญู"],
            "5": ["ภาษาจีน", "ครูกฤตพงศ์"],
            "6": ["พลศึกษา", "ครูประเดิมชัย"],
            "7": [],
            "8": []
        },
        "4": {
            "1": ["พระพุทธศาสนา", "ครูนิตยา"],
            "2": ["วิทยาศาสตร์", "ครูเผด็จ"],
            "3": ["ภาษาจีน", "ครูกฤตพงศ์"],
            "4": ["ภาษาอังกฤษ", "ครูฤทธิรงค์"],
            "5": ["HR", "ครูกฤตพงศ์"],
            "6": ["ภาษาจีน", "ครูกฤตพงศ์"],
            "7": [],
            "8": []
        },
        "5": {
            "1": ["การอ่าน", "ครูฤทธิรงค์"],
            "2": ["การอ่าน", "ครูWilliam"],
            "3": ["ภาษาจีน", "ครูกฤตพงศ์"]
        }
    }
}
