{
  "meta": {
    "branch": "วิทย์-คณิต",
    "teacher": [
      "ครูนิตยา พุ่มเพิ่ม",
      " "
    ],
    "room": "145"
  },
  "body": {
    "1": {
      "1": [
        "คณิตศาสตร์",
        "ครูพรรษวุฒิ"
      ],
      "2": [
        "พลศึกษา",
        "ครูจิรวัฒน์"
      ],
      "3": [
        "เคมี",
        "ครูรัชนี"
      ],
      "4": [
        "ฟิสิกส์",
        "ครูกวินพัฒน์"
      ],
      "5": [
        "แนะแนว"
      ],
      "6": [
        "สุขศึกษา",
        "ครูณัฐธินี"
      ],
      "7": [
        "ประวัติศาสตร์สากลฯ",
        "ครูนิตยา"
      ],
      "8": [
        "กิจกรรม"
      ]
    },
    "2": {
      "1": [
        "ชีววิทยา",
        "ครูนวสิน"
      ],
      "2": [
        "ภาษาไทย",
        "ครูลำพูน"
      ],
      "3": [
        "ฟิสิกส์",
        "ครูกวินพัฒน์"
      ],
      "4": [
        "ภาษาอังกฤษ",
        "ครูอสมาภรณ์"
      ],
      "5": [
        "คณิตศาสตร์",
        "ครูมนลดา"
      ],
      "6": [
        "เคมี",
        "ครูรัชนี"
      ],
      "7": [],
      "8": []
    },
    "3": {
      "1": [
        "ฟิสิกส์",
        "ครูกวินพัฒน์"
      ],
      "2": [
        "ฟิสิกส์",
        "ครูกวินพัฒน์"
      ],
      "3": [
        "คณิตศาสตร์",
        "ครูมนลดา"
      ],
      "4": [
        "คณิตศาสตร์",
        "ครูพรรษวุฒิ"
      ],
      "5": [
        "การอ่าน",
        "ครูอสมาภรณ์"
      ],
      "6": [
        "ชีววิทยา",
        "ครูนวสิน"
      ],
      "7": [
        "วิทยาศาสตร์",
        "ครูทอฉาย"
      ],
      "8": []
    },
    "4": {
      "1": [
        "คณิตศาสตร์",
        "ครูพรรษวุฒิ"
      ],
      "2": [
        "คณิตศาสตร์",
        "ครูมนลดา"
      ],
      "3": [
        "ชีววิทยา",
        "ครูนวสิน"
      ],
      "4": [
        "เคมี",
        "ครูรัชนี"
      ],
      "5": [
        "HR",
        "ครูนิตยา"
      ],
      "6": [
        "พระพุทธศาสนา",
        "ครูนิตยา"
      ],
      "7": [
        "การอ่าน",
        "ครู William"
      ],
      "8": []
    },
    "5": {
      "1": [
        "ภาษาอังกฤษ",
        "ครูอสมาภรณ์"
      ],
      "2": [
        "ภาษาไทย",
        "ครูลำพูน"
      ],
      "3": [
        "ประวัติศาสตร์สากลฯ",
        "ครูนิตยา"
      ]
    }
  }
}
