{
  "meta": {
    "branch": "ภาษา-ภาษาจีน",
    "teacher": [
      "ครูกฤตพงศ์ มูลมี",
      " "
    ],
    "room": "73"
  },
  "body": {
    "1": {
      "1": [
        "ภาษาจีน",
        "ครูกฤตพงศ์"
      ],
      "2": [
        "พระพุทธศาสนา",
        "ครูนิตยา"
      ],
      "3": [
        "ภาษาไทย",
        "ครูณัฐพัชร์"
      ],
      "4": [
        "แนะแนว"
      ],
      "5": [
        "ภาษาอังกฤษ",
        "ครูเปรมจิรัณ"
      ],
      "6": [
        "วิทยาศาสตร์",
        "ครูเผด็จ"
      ],
      "7": [
        "หลักภาษาไทย",
        "ครูสุรศักดิ์"
      ],
      "8": [
        "กิจกรรม"
      ]
    },
    "2": {
      "1": [
        "การอ่าน",
        "ครูเปรมจิรัณ"
      ],
      "2": [
        "คณิตศาสตร์",
        "ครูภราดร"
      ],
      "3": [
        "ภาษาจีน อ่าน-เขียน",
        "ครูกันต์กนิษฐ"
      ],
      "4": [
        "สุขศึกษา",
        "ครูจิรวัฒน์"
      ],
      "5": [
        "ภาษาจีน",
        "ครูกฤตพงศ์"
      ],
      "6": [
        "วิทยาศาสตร์",
        "ครูเผด็จ"
      ],
      "7": [],
      "8": []
    },
    "3": {
      "1": [
        "พลศึกษา",
        "ครูประเดิมชัย"
      ],
      "2": [
        "ภาษาจีน อ่าน-เขียน",
        "ครูกันต์กนิษฐ"
      ],
      "3": [
        "ภาษาจีน",
        "ครูกฤตพงศ์"
      ],
      "4": [
        "หลักภาษาไทย",
        "ครูสุรศักดิ์"
      ],
      "5": [
        "ภาษาจีนเพิ่มพูนฯ",
        "ครูกฤตพงศ์"
      ],
      "6": [
        "ประวัติศาสตร์สากลฯ",
        "ครูนิตยา"
      ],
      "7": [],
      "8": []
    },
    "4": {
      "1": [
        "ประวัติศาสตร์สากลฯ",
        "ครูนิตยา"
      ],
      "2": [
        "ภาษาไทย",
        "ครูณัฐพัชร์"
      ],
      "3": [
        "ภาษาจีนเพิ่มพูนฯ",
        "ครูกฤตพงศ์"
      ],
      "4": [
        "เสริมทักษะ",
        "ครู Michael"
      ],
      "5": [
        "HR",
        "ครูกฤตพงศ์"
      ],
      "6": [
        "คณิตศาสตร์",
        "ครูภราดร"
      ],
      "7": [],
      "8": []
    },
    "5": {
      "1": [
        "การอ่าน",
        "ครู James"
      ],
      "2": [
        "ภาษาอังกฤษ",
        "ครูเปรมจิรัณ"
      ],
      "3": [
        "ภาษาจีน",
        "ครูกฤตพงศ์"
      ]
    }
  }
}
